finam/__init__.py
finam/_version.py
finam/errors.py
finam/interfaces.py
finam/schedule.py
finam/adapters/__init__.py
finam/adapters/base.py
finam/adapters/probe.py
finam/adapters/regrid.py
finam/adapters/stats.py
finam/adapters/time.py
finam/adapters/time_integration.py
finam/components/__init__.py
finam/components/callback.py
finam/components/control.py
finam/components/debug.py
finam/components/generators.py
finam/components/mergers.py
finam/components/noise.py
finam/components/parametric.py
finam/components/readers.py
finam/components/writers.py
finam/data/__init__.py
finam/data/esri_tools.py
finam/data/grid_base.py
finam/data/grid_spec.py
finam/data/grid_tools.py
finam/data/tools/__init__.py
finam/data/tools/cf_units.py
finam/data/tools/core.py
finam/data/tools/info.py
finam/data/tools/mask.py
finam/data/tools/units.py
finam/sdk/__init__.py
finam/sdk/adapter.py
finam/sdk/component.py
finam/sdk/input.py
finam/sdk/output.py
finam/tools/__init__.py
finam/tools/connect_helper.py
finam/tools/cwd_helper.py
finam/tools/date_helper.py
finam/tools/enum_helper.py
finam/tools/inspect_helper.py
finam/tools/log_helper.py
finam/tools/wurlitzer.py
finam-1.0.1.dist-info/METADATA
finam-1.0.1.dist-info/WHEEL
finam-1.0.1.dist-info/licenses/AUTHORS.md
finam-1.0.1.dist-info/licenses/COPYING
finam-1.0.1.dist-info/licenses/COPYING.LESSER
finam-1.0.1.dist-info/licenses/LICENSE.md
finam-1.0.1.dist-info/RECORD
