Metadata-Version: 2.4
Name: finam
Version: 1.0.1
Summary: FINAM is not a model.
Project-URL: Homepage, https://FINAM.pages.ufz.de/
Project-URL: Documentation, https://FINAM.pages.ufz.de/finam/
Project-URL: Source, https://git.ufz.de/FINAM/finam
Project-URL: Tracker, https://git.ufz.de/FINAM/finam/-/issues
Project-URL: Changelog, https://git.ufz.de/FINAM/finam/-/blob/main/CHANGELOG.md
Author-email: FINAM Developers <finam@ufz.de>
License-Expression: LGPL-3.0
License-File: AUTHORS.md
License-File: COPYING
License-File: COPYING.LESSER
License-File: LICENSE.md
Classifier: Development Status :: 5 - Production/Stable
Classifier: Intended Audience :: Developers
Classifier: Intended Audience :: Education
Classifier: Intended Audience :: End Users/Desktop
Classifier: Intended Audience :: Science/Research
Classifier: License :: OSI Approved :: GNU Lesser General Public License v3 (LGPLv3)
Classifier: Natural Language :: English
Classifier: Operating System :: MacOS
Classifier: Operating System :: Microsoft
Classifier: Operating System :: Unix
Classifier: Programming Language :: Python
Classifier: Programming Language :: Python :: 3
Classifier: Programming Language :: Python :: 3 :: Only
Classifier: Programming Language :: Python :: 3.8
Classifier: Programming Language :: Python :: 3.9
Classifier: Programming Language :: Python :: 3.10
Classifier: Programming Language :: Python :: 3.11
Classifier: Programming Language :: Python :: 3.12
Classifier: Programming Language :: Python :: 3.13
Classifier: Topic :: Scientific/Engineering
Classifier: Topic :: Software Development
Classifier: Topic :: Utilities
Requires-Python: >=3.8
Requires-Dist: numpy>=1.17.0
Requires-Dist: opensimplex>=0.4
Requires-Dist: packaging
Requires-Dist: pandas>=1.3
Requires-Dist: pint!=0.24.0,>=0.20
Requires-Dist: pyevtk>=1.6.0
Requires-Dist: pyproj>=3.4
Requires-Dist: scipy>=1.9.0
Provides-Extra: doc
Requires-Dist: ablog>=0.10; extra == 'doc'
Requires-Dist: docutils>=0.18; extra == 'doc'
Requires-Dist: matplotlib>=3; extra == 'doc'
Requires-Dist: myst-parser>=1.0; extra == 'doc'
Requires-Dist: numpydoc>=1.1; extra == 'doc'
Requires-Dist: pydata-sphinx-theme==0.13; extra == 'doc'
Requires-Dist: sphinx-design>=0.4; extra == 'doc'
Requires-Dist: sphinx>=6; extra == 'doc'
Requires-Dist: sphinxcontrib-mermaid>=0.7; extra == 'doc'
Provides-Extra: test
Requires-Dist: pygal==3.0.0; extra == 'test'
Requires-Dist: pytest-benchmark[histogram]>=4.0; extra == 'test'
Requires-Dist: pytest-cov>=3; extra == 'test'
